{
  "date": "26.10.2020",
  "records": [
    {
      "serialNumber": 1,
      "zone": 2,
      "div": 19,
      "area": "106th Street,MMDA",
      "containmentInitiatedDate": "18.10.2020"
    },
    {
      "serialNumber": 2,
      "zone": 2,
      "div": 19,
      "area": "116th Street,MMDA",
      "containmentInitiatedDate": "17.10.2020"
    },
    {
      "serialNumber": 3,
      "zone": 2,
      "div": 21,
      "area": "Thamaraikullam Street, Manali",
      "containmentInitiatedDate": "17.10.2020"
    },
    {
      "serialNumber": 4,
      "zone": 4,
      "div": 35,
      "area": "KKD Nagar 5th Block 2nd Street",
      "containmentInitiatedDate": "14.10.2020"
    },
    {
      "serialNumber": 5,
      "zone": 5,
      "div": 55,
      "area": "Govindappa Street",
      "containmentInitiatedDate": "13.10.2020"
    },
    {
      "serialNumber": 6,
      "zone": 5,
      "div": 57,
      "area": "Irulappan Street",
      "containmentInitiatedDate": "13.10.2020"
    },
    {
      "serialNumber": 7,
      "zone": 5,
      "div": 57,
      "area": "Budraian Street",
      "containmentInitiatedDate": "13.10.2020"
    },
    {
      "serialNumber": 8,
      "zone": 8,
      "div": 106,
      "area": "Limeklin Street Aminjikarai,Ch-29",
      "containmentInitiatedDate": "14.10.2020"
    },
    {
      "serialNumber": 9,
      "zone": 9,
      "div": 111,
      "area": "Aziz Mulk Street,Choolaimedu",
      "containmentInitiatedDate": "14.10.2020"
    },
    {
      "serialNumber": 10,
      "zone": 9,
      "div": 124,
      "area": "Rakkiyappa Street",
      "containmentInitiatedDate": "14.10.2020"
    },
    {
      "serialNumber": 11,
      "zone": 13,
      "div": 176,
      "area": "Danakotti Raja Street,Ekkattuthangal",
      "containmentInitiatedDate": "14.10.2020"
    },
    {
      "serialNumber": 12,
      "zone": 15,
      "div": 195,
      "area": "Thiruvalluvar Street Okkiyam Petti",
      "containmentInitiatedDate": "17.10.2020"
    }
  ]
}